skilleter_extras/__init__.py
skilleter_extras/borger.py
skilleter_extras/console_colours.py
skilleter_extras/diskspacecheck.py
skilleter_extras/docker_purge.py
skilleter_extras/gphotosync.py
skilleter_extras/localphotosync.py
skilleter_extras/moviemover.py
skilleter_extras/photodupe.py
skilleter_extras/phototidier.py
skilleter_extras/rmdupe.py
skilleter_extras/splitpics.py
skilleter_extras/strreplace.py
skilleter_extras/sysmon.py
skilleter_extras/window_rename.py
skilleter_extras-0.0.6.dist-info/licenses/LICENSE
skilleter_extras-0.0.6.dist-info/METADATA
skilleter_extras-0.0.6.dist-info/WHEEL
skilleter_extras-0.0.6.dist-info/entry_points.txt
skilleter_extras-0.0.6.dist-info/top_level.txt
skilleter_extras-0.0.6.dist-info/RECORD
