Metadata-Version: 2.4
Name: skilleter_extras
Version: 0.0.6
Summary: A collection of useful personal utilities, separated from the core skilleter-thingy package
Author-email: John Skilleter <john@skilleter.org.uk>
Project-URL: Home, https://skilleter.org.uk
Project-URL: Repository, https://gitlab.com/skilleter/skilleter-extras
Project-URL: Issues, https://gitlab.com/skilleter/skilleter-extras/-/issues
Classifier: Programming Language :: Python :: 3
Classifier: License :: OSI Approved :: GNU General Public License v3 or later (GPLv3+)
Classifier: Operating System :: OS Independent
Requires-Python: >=3.8
License-File: LICENSE
Requires-Dist: skilleter-modules
Requires-Dist: psutil
Requires-Dist: pillow
Requires-Dist: imagehash
Requires-Dist: python-dateutil
Dynamic: license-file
